logosentinel/__init__.py
logosentinel/exceptions.py
logosentinel/handler.py
logosentinel/logger.py
logosentinel/middleware.py
logosentinel/sender.py
logosentinel/client/__init__.py
logosentinel/client/a_sync.py
logosentinel/client/sync.py
logosentinel/config/__init__.py
logosentinel/config/base.py
logosentinel/config/dev.py
logosentinel/config/prod.py
logosentinel/libs/__init__.py
logosentinel/libs/utils.py
logsentinel-0.1.2.dist-info/METADATA
logsentinel-0.1.2.dist-info/WHEEL
logsentinel-0.1.2.dist-info/RECORD
