Metadata-Version: 2.4
Name: logsentinel
Version: 0.1.2
Summary: AI-powered log monitoring SDK for Python applications
Project-URL: Homepage, https://github.com/inctifra/logsentinel
Project-URL: Documentation, https://pypi.org/project/logsentinel
Project-URL: Source, https://github.com/inctifra/logsentinel
Author-email: Jeckonia Kwasa <inctifra@gmail.com>
License: MIT
Requires-Python: >=3.9
Requires-Dist: aiohttp>=3.13.2
Requires-Dist: backoff>=2.2.1
Requires-Dist: django-environ>=0.12.0
Requires-Dist: fastapi[all]>=0.121.1
Requires-Dist: httpx>=0.28.1
Requires-Dist: requests>=2.32.3
Requires-Dist: rich>=14.2.0
